{"assets/gif/1.gif":["assets/gif/1.gif"],"assets/gif/hospital.gif":["assets/gif/hospital.gif"],"assets/gif/s1.gif":["assets/gif/s1.gif"],"assets/images/1.jpg":["assets/images/1.jpg"],"assets/images/2.jpg":["assets/images/2.jpg"],"assets/images/3.png":["assets/images/3.png"],"assets/images/doctor.jpg":["assets/images/doctor.jpg"],"assets/images/doctor2.jpg":["assets/images/doctor2.jpg"],"assets/images/doctor3.jpg":["assets/images/doctor3.jpg"],"assets/images/hospital-buildings.png":["assets/images/hospital-buildings.png"],"assets/images/whatsapp.png":["assets/images/whatsapp.png"],"packages/cupertino_icons/assets/CupertinoIcons.ttf":["packages/cupertino_icons/assets/CupertinoIcons.ttf"]}